mavlink/mavlink.py
mavlink-0.1.0.dist-info/METADATA
mavlink-0.1.0.dist-info/WHEEL
mavlink-0.1.0.dist-info/top_level.txt
mavlink-0.1.0.dist-info/RECORD
