Metadata-Version: 2.4
Name: mavlink
Version: 0.1.0
Summary: mdhk mavlink lib
Author-email: Your Name <you@example.com>
Classifier: Programming Language :: Python :: 3
Classifier: License :: OSI Approved :: MIT License
Requires-Python: >=3.6
